{
  "Democracy": {
    "Ship Modules": [],
    "Stratagems": [
      {
        "ActivationTime": "3",
        "Uses": "Unlimited",
        "Name": "Orbital Precision Strike",
        "Aliases": [
          "Orbital Precision Strike"
        ],
        "Code": "RRU",
        "Cooldown": "100"
      },
      {
        "ActivationTime": "2.05",
        "Uses": "Unlimited",
        "Name": "Orbital Gatling Barrage",
        "Aliases": [
          "Orbital Gatling Barrage"
        ],
        "Code": "RDLUU",
        "Cooldown": "70"
      },
      {
        "ActivationTime": "3.45",
        "Uses": "Unlimited",
        "Name": "Orbital Airburst Strike",
        "Aliases": [
          "Orbital Airburst Strike"
        ],
        "Code": "RRR",
        "Cooldown": "100"
      },
      {
        "ActivationTime": "6.45",
        "Uses": "Unlimited",
        "Name": "Orbital Napalm Barrage",
        "Aliases": [
          "Orbital Napalm Barrage"
        ],
        "Code": "RRDLRU",
        "Cooldown": "240"
      },
      {
        "ActivationTime": "6.45",
        "Uses": "Unlimited",
        "Name": "Orbital 120MM HE Barrage",
        "Aliases": [
          "Orbital 120MM HE Barrage"
        ],
        "Code": "RRDLRD",
        "Cooldown": "180"
      },
      {
        "ActivationTime": "4.45",
        "Uses": "Unlimited",
        "Name": "Orbital Walking Barrage",
        "Aliases": [
          "Orbital Walking Barrage"
        ],
        "Code": "RDRDRD",
        "Cooldown": "240"
      },
      {
        "ActivationTime": "7.45",
        "Uses": "Unlimited",
        "Name": "Orbital 380MM HE Barrage",
        "Aliases": [
          "Orbital 380MM HE Barrage"
        ],
        "Code": "RDUULDD",
        "Cooldown": "240"
      },
      {
        "ActivationTime": "0",
        "Uses": "Unlimited",
        "Name": "Orbital Railcannon Strike",
        "Aliases": [
          "Orbital Railcannon Strike"
        ],
        "Code": "RUDDR",
        "Cooldown": "210"
      },
      {
        "ActivationTime": "1",
        "Uses": "3",
        "Name": "Orbital Laser",
        "Aliases": [
          "Orbital Laser"
        ],
        "Code": "RDURD",
        "Cooldown": "300"
      },
      {
        "ActivationTime": "3.45",
        "Uses": "Unlimited",
        "Name": "Orbital EMS Strike",
        "Aliases": [
          "Orbital EMS Strike"
        ],
        "Code": "RRLD",
        "Cooldown": "75"
      },
      {
        "ActivationTime": "3.45",
        "Uses": "Unlimited",
        "Name": "Orbital Gas Strike",
        "Aliases": [
          "Orbital Gas Strike"
        ],
        "Code": "RRDR",
        "Cooldown": "75"
      },
      {
        "ActivationTime": "3.45",
        "Uses": "Unlimited",
        "Name": "Orbital Smoke Strike",
        "Aliases": [
          "Orbital Smoke Strike"
        ],
        "Code": "RRDU",
        "Cooldown": "100"
      },
      {
        "ActivationTime": "3.45",
        "Uses": "1",
        "Name": "Eagle 500kg Bomb",
        "Aliases": [
          "Eagle 500kg Bomb"
        ],
        "Code": "URDDD",
        "Cooldown": "8"
      },
      {
        "ActivationTime": "2.4",
        "Uses": "4",
        "Name": "Eagle Strafing Run",
        "Aliases": [
          "Eagle Strafing Run"
        ],
        "Code": "URR",
        "Cooldown": "8"
      },
      {
        "ActivationTime": "3.4",
        "Uses": "2",
        "Name": "Eagle 110MM Rocket Pods",
        "Aliases": [
          "Eagle 110MM Rocket Pods"
        ],
        "Code": "URUL",
        "Cooldown": "8"
      },
      {
        "ActivationTime": "4.1",
        "Uses": "2",
        "Name": "Eagle Airstrike",
        "Aliases": [
          "Eagle Airstrike"
        ],
        "Code": "URDR",
        "Cooldown": "8"
      },
      {
        "ActivationTime": "4.35",
        "Uses": "4",
        "Name": "Eagle Cluster Bomb",
        "Aliases": [
          "Eagle Cluster Bomb"
        ],
        "Code": "URDDR",
        "Cooldown": "8"
      },
      {
        "ActivationTime": "4.1",
        "Uses": "2",
        "Name": "Eagle Napalm Airstrike",
        "Aliases": [
          "Eagle Napalm Airstrike"
        ],
        "Code": "URDU",
        "Cooldown": "8"
      },
      {
        "ActivationTime": "4.4",
        "Uses": "2",
        "Name": "Eagle Smoke Strike",
        "Aliases": [
          "Eagle Smoke Strike"
        ],
        "Code": "URUD",
        "Cooldown": "8"
      },
      {
        "ActivationTime": "4.75",
        "Uses": "Unlimited",
        "Name": "CQC-1 One True Flag",
        "Aliases": [
          "CQC-1",
          "One True Flag"
        ],
        "Code": "DLRRU",
        "Cooldown": "480"
      },
      {
        "ActivationTime": "4.75",
        "Uses": "Unlimited",
        "Name": "MG-43 Machine Gun",
        "Aliases": [
          "MG-43",
          "Machine Gun"
        ],
        "Code": "DLDUR",
        "Cooldown": "480"
      },
      {
        "ActivationTime": "4.75",
        "Uses": "Unlimited",
        "Name": "M-105 Stalwart",
        "Aliases": [
          "M-105",
          "Stalwart"
        ],
        "Code": "DLDUUL",
        "Cooldown": "480"
      },
      {
        "ActivationTime": "4.75",
        "Uses": "Unlimited",
        "Name": "MG-206 Heavy Machine Gun",
        "Aliases": [
          "MG-206",
          "Heavy Machine Gun"
        ],
        "Code": "DLUDD",
        "Cooldown": "480"
      },
      {
        "ActivationTime": "4.75",
        "Uses": "Unlimited",
        "Name": "RS-422 Railgun",
        "Aliases": [
          "RS-422",
          "Railgun"
        ],
        "Code": "DRDULR",
        "Cooldown": "480"
      },
      {
        "ActivationTime": "4.75",
        "Uses": "Unlimited",
        "Name": "APW-1 Anti-Materiel Rifle",
        "Aliases": [
          "APW-1",
          "Anti-Materiel Rifle"
        ],
        "Code": "DLRUD",
        "Cooldown": "480"
      },
      {
        "ActivationTime": "4.75",
        "Uses": "Unlimited",
        "Name": "GL-21 Grenade Launcher",
        "Aliases": [
          "GL-21",
          "Grenade Launcher"
        ],
        "Code": "DLULD",
        "Cooldown": "480"
      },
      {
        "ActivationTime": "4.75",
        "Uses": "Unlimited",
        "Name": "GL-52 De-Escalator",
        "Aliases": [
          "GL-52",
          "De-Escalator"
        ],
        "Code": "DRULR",
        "Cooldown": "480"
      },
      {
        "ActivationTime": "4.75",
        "Uses": "Unlimited",
        "Name": "TX-41 Sterilizer",
        "Aliases": [
          "TX-41",
          "Sterilizer"
        ],
        "Code": "DLUDL",
        "Cooldown": "480"
      },
      {
        "ActivationTime": "4.75",
        "Uses": "Unlimited",
        "Name": "FLAM-40 Flamethrower",
        "Aliases": [
          "FLAM-40",
          "Flamethrower"
        ],
        "Code": "DLUDU",
        "Cooldown": "480"
      },
      {
        "ActivationTime": "4.75",
        "Uses": "Unlimited",
        "Name": "LAS-98 Laser Cannon",
        "Aliases": [
          "LAS-98",
          "Laser Cannon"
        ],
        "Code": "DLDUL",
        "Cooldown": "480"
      },
      {
        "ActivationTime": "4.75",
        "Uses": "Unlimited",
        "Name": "LAS-99 Quasar Cannon",
        "Aliases": [
          "LAS-99",
          "Quasar Cannon"
        ],
        "Code": "DDULR",
        "Cooldown": "480"
      },
      {
        "ActivationTime": "4.75",
        "Uses": "Unlimited",
        "Name": "ARC-3 Arc Thrower",
        "Aliases": [
          "ARC-3",
          "Arc Thrower"
        ],
        "Code": "DRDULL",
        "Cooldown": "480"
      },
      {
        "ActivationTime": "4.75",
        "Uses": "Unlimited",
        "Name": "MLS-4X Commando",
        "Aliases": [
          "MLS-4X",
          "Commando"
        ],
        "Code": "DLUDR",
        "Cooldown": "120"
      },
      {
        "ActivationTime": "4.75",
        "Uses": "Unlimited",
        "Name": "EAT-17 Expendable Anti-Tank",
        "Aliases": [
          "EAT-17",
          "Expendable Anti-Tank"
        ],
        "Code": "DDLUR",
        "Cooldown": "70"
      },
      {
        "ActivationTime": "4.75",
        "Uses": "Unlimited",
        "Name": "AC-8 Autocannon",
        "Aliases": [
          "AC-8",
          "Autocannon"
        ],
        "Code": "DLDUUR",
        "Cooldown": "480"
      },
      {
        "ActivationTime": "4.75",
        "Uses": "Unlimited",
        "Name": "RL-77 Airburst Rocket Launcher",
        "Aliases": [
          "RL-77",
          "Airburst Rocket Launcher"
        ],
        "Code": "DUULR",
        "Cooldown": "480"
      },
      {
        "ActivationTime": "4.75",
        "Uses": "Unlimited",
        "Name": "FAF-14 Spear",
        "Aliases": [
          "FAF-14",
          "Spear"
        ],
        "Code": "DDUDD",
        "Cooldown": "480"
      },
      {
        "ActivationTime": "7.75",
        "Uses": "Unlimited",
        "Name": "StA-X3 W.A.S.P. Launcher",
        "Aliases": [
          "StA-X3",
          "W.A.S.P. Launcher"
        ],
        "Code": "DDUDR",
        "Cooldown": "432"
      },
      {
        "ActivationTime": "4.75",
        "Uses": "Unlimited",
        "Name": "GR-8 Recoilless Rifle",
        "Aliases": [
          "GR-8",
          "Recoilless Rifle"
        ],
        "Code": "DLRRL",
        "Cooldown": "480"
      },
      {
        "ActivationTime": "9.75",
        "Uses": "Unlimited",
        "Name": "Backpacks#Supply Pack",
        "Aliases": [
          "Backpacks#Supply Pack"
        ],
        "Code": "DLDUUD",
        "Cooldown": "480"
      },
      {
        "ActivationTime": "9.75",
        "Uses": "Unlimited",
        "Name": "B-100 Portable Hellbomb",
        "Aliases": [
          "B-100",
          "Portable Hellbomb"
        ],
        "Code": "DRUUU",
        "Cooldown": "300"
      },
      {
        "ActivationTime": "9.75",
        "Uses": "Unlimited",
        "Name": "LIFT-860 Hover Pack",
        "Aliases": [
          "LIFT-860",
          "Hover Pack"
        ],
        "Code": "DUUDLR",
        "Cooldown": "480"
      },
      {
        "ActivationTime": "9.75",
        "Uses": "Unlimited",
        "Name": "Backpacks#Jump Pack",
        "Aliases": [
          "Backpacks#Jump Pack"
        ],
        "Code": "DUUDU",
        "Cooldown": "480"
      },
      {
        "ActivationTime": "9.75",
        "Uses": "Unlimited",
        "Name": "Backpacks#Shield Generator Pack",
        "Aliases": [
          "Backpacks#Shield Generator Pack"
        ],
        "Code": "DULRLR",
        "Cooldown": "480"
      },
      {
        "ActivationTime": "9.75",
        "Uses": "Unlimited",
        "Name": "Backpacks#Directional Shield",
        "Aliases": [
          "Backpacks#Directional Shield"
        ],
        "Code": "DULRUU",
        "Cooldown": "300"
      },
      {
        "ActivationTime": "9.75",
        "Uses": "Unlimited",
        "Name": "Backpacks#Ballistic Shield",
        "Aliases": [
          "Backpacks#Ballistic Shield"
        ],
        "Code": "DLDDUL",
        "Cooldown": "300"
      },
      {
        "ActivationTime": "9.75",
        "Uses": "Unlimited",
        "Name": "AX/ARC-3 Guard Dog K-9",
        "Aliases": [
          "AX/ARC-3",
          "Guard Dog K-9"
        ],
        "Code": "DULURL",
        "Cooldown": "480"
      },
      {
        "ActivationTime": "9.75",
        "Uses": "Unlimited",
        "Name": "Backpacks#Guard Dog",
        "Aliases": [
          "Backpacks#Guard Dog"
        ],
        "Code": "DULURD",
        "Cooldown": "480"
      },
      {
        "ActivationTime": "9.75",
        "Uses": "Unlimited",
        "Name": "Backpacks#Guard Dog Rover",
        "Aliases": [
          "Backpacks#Guard Dog Rover"
        ],
        "Code": "DULURR",
        "Cooldown": "480"
      },
      {
        "ActivationTime": "9.75",
        "Uses": "Unlimited",
        "Name": "Backpacks#Guard Dog Dog Breath",
        "Aliases": [
          "Backpacks#Guard Dog Dog Breath"
        ],
        "Code": "DULURU",
        "Cooldown": "480"
      },
      {
        "ActivationTime": "10.50",
        "Uses": "Unlimited",
        "Name": "M-102 Fast Recon Vehicle",
        "Aliases": [
          "M-102",
          "Fast Recon Vehicle"
        ],
        "Code": "LDRDRDU",
        "Cooldown": "480"
      },
      {
        "ActivationTime": "10.5",
        "Uses": "3",
        "Name": "EXO-49 Emancipator Exosuit",
        "Aliases": [
          "EXO-49",
          "Emancipator Exosuit"
        ],
        "Code": "LDRULDU",
        "Cooldown": "600"
      },
      {
        "ActivationTime": "10.5",
        "Uses": "3",
        "Name": "EXO-45 Patriot Exosuit",
        "Aliases": [
          "EXO-45",
          "Patriot Exosuit"
        ],
        "Code": "LDRULDD",
        "Cooldown": "600"
      },
      {
        "ActivationTime": "10,5",
        "Uses": "Unlimited",
        "Name": "TD-220 Bastion",
        "Aliases": [
          "TD-220",
          "Bastion"
        ],
        "Code": "LDRDLDU",
        "Cooldown": "780"
      },
      {
        "ActivationTime": "4.75",
        "Uses": "Unlimited",
        "Name": "Sentries#Gatling",
        "Aliases": [
          "Sentries#Gatling"
        ],
        "Code": "DURL",
        "Cooldown": "180"
      },
      {
        "ActivationTime": "4.75",
        "Uses": "Unlimited",
        "Name": "Sentries#Machine Gun",
        "Aliases": [
          "Sentries#Machine Gun"
        ],
        "Code": "DURRU",
        "Cooldown": "120"
      },
      {
        "ActivationTime": "4.75",
        "Uses": "Unlimited",
        "Name": "Sentries#Flame",
        "Aliases": [
          "Sentries#Flame"
        ],
        "Code": "DURDUU",
        "Cooldown": "150"
      },
      {
        "ActivationTime": "4.75",
        "Uses": "Unlimited",
        "Name": "Sentries#Rocket",
        "Aliases": [
          "Sentries#Rocket"
        ],
        "Code": "DURRL",
        "Cooldown": "180"
      },
      {
        "ActivationTime": "4.75",
        "Uses": "Unlimited",
        "Name": "Sentries#Autocannon",
        "Aliases": [
          "Sentries#Autocannon"
        ],
        "Code": "DURULU",
        "Cooldown": "180"
      },
      {
        "ActivationTime": "4.75",
        "Uses": "Unlimited",
        "Name": "Sentries#EMS Mortar",
        "Aliases": [
          "Sentries#EMS Mortar"
        ],
        "Code": "DURDR",
        "Cooldown": "180"
      },
      {
        "ActivationTime": "4.75",
        "Uses": "Unlimited",
        "Name": "Sentries#Mortar",
        "Aliases": [
          "Sentries#Mortar"
        ],
        "Code": "DURRD",
        "Cooldown": "180"
      },
      {
        "ActivationTime": "4.75",
        "Uses": "Unlimited",
        "Name": "FX-12 Shield Generator Relay",
        "Aliases": [
          "FX-12",
          "Shield Generator Relay"
        ],
        "Code": "DDLRLR",
        "Cooldown": "90"
      },
      {
        "ActivationTime": "4.75",
        "Uses": "Unlimited",
        "Name": "E/GL-21 Grenadier Battlement",
        "Aliases": [
          "E/GL-21",
          "Grenadier Battlement"
        ],
        "Code": "DRDLR",
        "Cooldown": "180"
      },
      {
        "ActivationTime": "4.75",
        "Uses": "Unlimited",
        "Name": "E/AT-12 Anti-Tank Emplacement",
        "Aliases": [
          "E/AT-12",
          "Anti-Tank Emplacement"
        ],
        "Code": "DULRRR",
        "Cooldown": "180"
      },
      {
        "ActivationTime": "4.75",
        "Uses": "Unlimited",
        "Name": "E/MG-101 HMG Emplacement",
        "Aliases": [
          "E/MG-101",
          "HMG Emplacement"
        ],
        "Code": "DULRRL",
        "Cooldown": "180"
      },
      {
        "ActivationTime": "4.75",
        "Uses": "Unlimited",
        "Name": "Sentries#Tesla",
        "Aliases": [
          "Sentries#Tesla"
        ],
        "Code": "DURULR",
        "Cooldown": "150"
      },
      {
        "ActivationTime": "4.75",
        "Uses": "Unlimited",
        "Name": "MD-17 Anti-Tank Mines",
        "Aliases": [
          "MD-17",
          "Anti-Tank Mines"
        ],
        "Code": "DLUU",
        "Cooldown": "180"
      },
      {
        "ActivationTime": "4.75",
        "Uses": "Unlimited",
        "Name": "MD-8 Gas Mines",
        "Aliases": [
          "MD-8",
          "Gas Mines"
        ],
        "Code": "DLLR",
        "Cooldown": "180"
      },
      {
        "ActivationTime": "4.75",
        "Uses": "Unlimited",
        "Name": "MD-6 Anti-Personnel Minefield",
        "Aliases": [
          "MD-6",
          "Anti-Personnel Minefield"
        ],
        "Code": "DLUR",
        "Cooldown": "180"
      },
      {
        "ActivationTime": "4.75",
        "Uses": "Unlimited",
        "Name": "Mines#Incendiary_Mines",
        "Aliases": [
          "Mines#Incendiary_Mines"
        ],
        "Code": "DLLD",
        "Cooldown": "180"
      },
      {
        "ActivationTime": "5",
        "Uses": "5 per Person",
        "Name": "Reinforce",
        "Aliases": [
          "Reinforce"
        ],
        "Code": "UDRLU",
        "Cooldown": "120s"
      },
      {
        "ActivationTime": "5",
        "Uses": "1",
        "Name": "SOS Beacon",
        "Aliases": [
          "SOS Beacon"
        ],
        "Code": "UDRU",
        "Cooldown": "N/A"
      },
      {
        "ActivationTime": "12",
        "Uses": "Unlimited",
        "Name": "Resupply",
        "Aliases": [
          "Resupply"
        ],
        "Code": "DDUR",
        "Cooldown": "160"
      },
      {
        "ActivationTime": "6",
        "Uses": "Unlimited",
        "Name": "NUX-223 Hellbomb",
        "Aliases": [
          "NUX-223",
          "Hellbomb"
        ],
        "Code": "DULDURDU",
        "Cooldown": "30"
      },
      {
        "ActivationTime": "N/A",
        "Uses": "1 per objective",
        "Name": "SSSD Delivery",
        "Aliases": [
          "SSSD Delivery"
        ],
        "Code": "DDDUU",
        "Cooldown": "N/A"
      },
      {
        "ActivationTime": "9",
        "Uses": "1 per objective",
        "Name": "Seismic Probe",
        "Aliases": [
          "Seismic Probe"
        ],
        "Code": "UULRDD",
        "Cooldown": "N/A"
      },
      {
        "ActivationTime": "N/A",
        "Uses": "Unlimited",
        "Name": "Upload Data",
        "Aliases": [
          "Upload Data"
        ],
        "Code": "LRUUU",
        "Cooldown": "N/A"
      },
      {
        "ActivationTime": "N/A",
        "Uses": "Unlimited",
        "Name": "Eagle#General Tips",
        "Aliases": [
          "Eagle#General Tips"
        ],
        "Code": "UULUR",
        "Cooldown": "2 minutes"
      },
      {
        "ActivationTime": "N/A",
        "Uses": "5",
        "Name": "SEAF Artillery",
        "Aliases": [
          "SEAF Artillery"
        ],
        "Code": "RUUD",
        "Cooldown": "N/A"
      },
      {
        "ActivationTime": "N/A",
        "Uses": "N/A",
        "Name": "Super Earth Flag",
        "Aliases": [
          "Super Earth Flag"
        ],
        "Code": "DUDU",
        "Cooldown": "N/A"
      },
      {
        "ActivationTime": "N/A",
        "Uses": "1 per objective",
        "Name": "Hive Breaker Drill",
        "Aliases": [
          "Hive Breaker Drill"
        ],
        "Code": "LUDRDD",
        "Cooldown": "N/A"
      }
    ]
  }
}
